bcb_deep_equal/__init__.py
bcb_deep_equal/constants.py
bcb_deep_equal/deep_equal.py
bcb_deep_equal/py.typed
bcb_deep_equal-0.1.2.dist-info/licenses/LICENSE
bcb_deep_equal-0.1.2.dist-info/METADATA
bcb_deep_equal-0.1.2.dist-info/WHEEL
bcb_deep_equal-0.1.2.dist-info/top_level.txt
bcb_deep_equal-0.1.2.dist-info/RECORD
