Metadata-Version: 2.4
Name: bcb-deep-equal
Version: 0.1.2
Summary: Floating-point tolerant comparison for BigCodeBench
Author: edward-lcl
Maintainer: edward-lcl
License: MIT
Project-URL: Homepage, https://github.com/edward-lcl/bcb-deep-equal
Project-URL: Bug Reports, https://github.com/edward-lcl/bcb-deep-equal/issues
Project-URL: Source, https://github.com/edward-lcl/bcb-deep-equal
Keywords: bigcodebench,bcb,floating-point,comparison,testing,deep-equal,tolerance
Classifier: Development Status :: 4 - Beta
Classifier: Intended Audience :: Developers
Classifier: License :: OSI Approved :: MIT License
Classifier: Programming Language :: Python :: 3
Classifier: Programming Language :: Python :: 3.8
Classifier: Programming Language :: Python :: 3.9
Classifier: Programming Language :: Python :: 3.10
Classifier: Programming Language :: Python :: 3.11
Classifier: Programming Language :: Python :: 3.12
Classifier: Topic :: Software Development :: Testing
Classifier: Topic :: Scientific/Engineering :: Mathematics
Requires-Python: >=3.8
License-File: LICENSE
Provides-Extra: numpy
Requires-Dist: numpy>=1.19.0; extra == "numpy"
Provides-Extra: pandas
Requires-Dist: pandas>=1.0.0; extra == "pandas"
Provides-Extra: all
Requires-Dist: numpy>=1.19.0; extra == "all"
Requires-Dist: pandas>=1.0.0; extra == "all"
Provides-Extra: dev
Requires-Dist: pytest>=6.0; extra == "dev"
Requires-Dist: pytest-cov>=2.0; extra == "dev"
Requires-Dist: numpy>=1.19.0; extra == "dev"
Requires-Dist: pandas>=1.0.0; extra == "dev"
Requires-Dist: black>=22.0; extra == "dev"
Requires-Dist: mypy>=0.950; extra == "dev"
Requires-Dist: ruff>=0.0.261; extra == "dev"
Dynamic: license-file
